pycparser_fake_libc/__init__.py
pycparser_fake_libc/_ansi.h
pycparser_fake_libc/_fake_defines.h
pycparser_fake_libc/_fake_typedefs.h
pycparser_fake_libc/_syslist.h
pycparser_fake_libc/aio.h
pycparser_fake_libc/alloca.h
pycparser_fake_libc/ar.h
pycparser_fake_libc/argz.h
pycparser_fake_libc/assert.h
pycparser_fake_libc/complex.h
pycparser_fake_libc/cpio.h
pycparser_fake_libc/ctype.h
pycparser_fake_libc/dirent.h
pycparser_fake_libc/dlfcn.h
pycparser_fake_libc/emmintrin.h
pycparser_fake_libc/endian.h
pycparser_fake_libc/envz.h
pycparser_fake_libc/errno.h
pycparser_fake_libc/fastmath.h
pycparser_fake_libc/fcntl.h
pycparser_fake_libc/features.h
pycparser_fake_libc/fenv.h
pycparser_fake_libc/float.h
pycparser_fake_libc/fmtmsg.h
pycparser_fake_libc/fnmatch.h
pycparser_fake_libc/ftw.h
pycparser_fake_libc/getopt.h
pycparser_fake_libc/glob.h
pycparser_fake_libc/grp.h
pycparser_fake_libc/iconv.h
pycparser_fake_libc/ieeefp.h
pycparser_fake_libc/immintrin.h
pycparser_fake_libc/inttypes.h
pycparser_fake_libc/iso646.h
pycparser_fake_libc/langinfo.h
pycparser_fake_libc/libgen.h
pycparser_fake_libc/libintl.h
pycparser_fake_libc/limits.h
pycparser_fake_libc/locale.h
pycparser_fake_libc/malloc.h
pycparser_fake_libc/math.h
pycparser_fake_libc/monetary.h
pycparser_fake_libc/mqueue.h
pycparser_fake_libc/ndbm.h
pycparser_fake_libc/netdb.h
pycparser_fake_libc/newlib.h
pycparser_fake_libc/nl_types.h
pycparser_fake_libc/paths.h
pycparser_fake_libc/poll.h
pycparser_fake_libc/process.h
pycparser_fake_libc/pthread.h
pycparser_fake_libc/pwd.h
pycparser_fake_libc/reent.h
pycparser_fake_libc/regdef.h
pycparser_fake_libc/regex.h
pycparser_fake_libc/sched.h
pycparser_fake_libc/search.h
pycparser_fake_libc/semaphore.h
pycparser_fake_libc/setjmp.h
pycparser_fake_libc/signal.h
pycparser_fake_libc/smmintrin.h
pycparser_fake_libc/spawn.h
pycparser_fake_libc/stdalign.h
pycparser_fake_libc/stdarg.h
pycparser_fake_libc/stdatomic.h
pycparser_fake_libc/stdbool.h
pycparser_fake_libc/stddef.h
pycparser_fake_libc-2.21.dist-info/METADATA
pycparser_fake_libc-2.21.dist-info/WHEEL
pycparser_fake_libc-2.21.dist-info/top_level.txt
pycparser_fake_libc-2.21.dist-info/RECORD
