Metadata-Version: 2.1
Name: pycparser-fake-libc
Version: 2.21
Summary: Pip-installable package with pycparser's fake libc headers
Home-page: https://github.com/ThomasGerstenberg/pycparser-fake-libc
Author: Thomas Gerstenberg
Author-email: tgerst6@gmail.com
License: UNKNOWN
Keywords: pycparser
Platform: UNKNOWN
